backports_datetime_fromisoformat-2.0.2.dist-info/LICENSE
backports_datetime_fromisoformat-2.0.2.dist-info/METADATA
backports_datetime_fromisoformat-2.0.2.dist-info/top_level.txt
backports_datetime_fromisoformat-2.0.2.dist-info/RECORD
backports_datetime_fromisoformat-2.0.2.dist-info/WHEEL
backports/_datetime_fromisoformat.cpython-39-aarch64-linux-gnu.so
backports/__init__.py
backports/datetime_fromisoformat/_datetimemodule.c
backports/datetime_fromisoformat/timezone.c
backports/datetime_fromisoformat/__init__.py
backports/datetime_fromisoformat/timezone.h
backports/datetime_fromisoformat/_datetimemodule.h
backports/datetime_fromisoformat/module.c
