Metadata-Version: 2.1
Name: backports-datetime-fromisoformat
Version: 2.0.2
Summary: Backport of Python 3.11's datetime.fromisoformat
Author-email: Michael Overmeyer <backports@movermeyer.com>
License: MIT License
Project-URL: Homepage, https://github.com/movermeyer/backports.datetime_fromisoformat
Project-URL: Documentation, https://github.com/movermeyer/backports.datetime_fromisoformat
Project-URL: Repository, https://github.com/movermeyer/backports.datetime_fromisoformat
Project-URL: Bug Tracker, https://github.com/movermeyer/backports.datetime_fromisoformat/issues
Project-URL: Changelog, https://github.com/movermeyer/backports.datetime_fromisoformat/CHANGELOG.md
Classifier: Intended Audience :: Developers
Classifier: License :: OSI Approved :: MIT License
Classifier: Operating System :: OS Independent
Classifier: Programming Language :: Python
Classifier: Programming Language :: Python :: 3
Classifier: Programming Language :: Python :: 3.4
Classifier: Programming Language :: Python :: 3.5
Classifier: Programming Language :: Python :: 3.6
Classifier: Programming Language :: Python :: 3.7
Classifier: Programming Language :: Python :: 3.8
Classifier: Programming Language :: Python :: 3.9
Classifier: Programming Language :: Python :: 3.10
Classifier: Topic :: Software Development :: Libraries :: Python Modules
Requires-Python: >3
License-File: LICENSE
